geomapforfun/__init__.py
geomapforfun/common.py
geomapforfun/geomapforfun.py
geomapforfun-0.0.1.dist-info/licenses/LICENSE
geomapforfun-0.0.1.dist-info/METADATA
geomapforfun-0.0.1.dist-info/WHEEL
geomapforfun-0.0.1.dist-info/entry_points.txt
geomapforfun-0.0.1.dist-info/top_level.txt
geomapforfun-0.0.1.dist-info/RECORD
